mcp_search_server/__init__.py
mcp_search_server/cache_store.py
mcp_search_server/config_loader.py
mcp_search_server/enrich.py
mcp_search_server/result_utils.py
mcp_search_server/server.py
mcp_search_server/utils.py
mcp_search_server/tools/__init__.py
mcp_search_server/tools/arxiv.py
mcp_search_server/tools/calculator.py
mcp_search_server/tools/credibility.py
mcp_search_server/tools/datetime_tool.py
mcp_search_server/tools/duckduckgo.py
mcp_search_server/tools/file_manager.py
mcp_search_server/tools/gdelt.py
mcp_search_server/tools/geolocation.py
mcp_search_server/tools/github.py
mcp_search_server/tools/link_parser.py
mcp_search_server/tools/maps_tool.py
mcp_search_server/tools/pdf_parser.py
mcp_search_server/tools/pubmed.py
mcp_search_server/tools/reddit.py
mcp_search_server/tools/rss_tool.py
mcp_search_server/tools/search_engine_base.py
mcp_search_server/tools/search_manager.py
mcp_search_server/tools/summarizer.py
mcp_search_server/tools/unified_search.py
mcp_search_server/tools/wikipedia.py
mcp_search_server-0.1.9.dist-info/licenses/LICENSE
mcp_search_server-0.1.9.dist-info/METADATA
mcp_search_server-0.1.9.dist-info/WHEEL
mcp_search_server-0.1.9.dist-info/entry_points.txt
mcp_search_server-0.1.9.dist-info/top_level.txt
mcp_search_server-0.1.9.dist-info/RECORD
