Metadata-Version: 2.4
Name: mcp-search-server
Version: 0.1.9
Summary: MCP server for web search, PDF parsing, and content extraction
Author-email: Artem K <kazkozdev@gmail.com>
License: MIT
Requires-Python: >=3.10
License-File: LICENSE
Requires-Dist: mcp>=0.9.0
Requires-Dist: aiohttp>=3.9.0
Requires-Dist: beautifulsoup4>=4.12.0
Requires-Dist: newspaper3k>=0.2.8
Requires-Dist: readability-lxml>=0.8.1
Requires-Dist: trafilatura>=2.0.0
Requires-Dist: PyPDF2>=3.0.0
Requires-Dist: pdfplumber>=0.10.0
Requires-Dist: wikipedia-api>=0.6.0
Requires-Dist: pytz>=2024.0
Requires-Dist: feedparser>=6.0.11
Requires-Dist: httpx>=0.28.1
Requires-Dist: requests>=2.32.5
Requires-Dist: selenium>=4.0.0
Requires-Dist: webdriver-manager>=4.0.0
Requires-Dist: undetected-chromedriver>=3.5.0
Requires-Dist: ddgs>=0.1.0
Requires-Dist: biopython>=1.83
Requires-Dist: gdeltdoc>=1.0.0
Requires-Dist: arxiv>=2.0.0
Requires-Dist: certifi>=2024.0.0
Provides-Extra: dev
Requires-Dist: pytest>=7.0.0; extra == "dev"
Requires-Dist: pytest-asyncio>=0.21.0; extra == "dev"
Requires-Dist: pytest-cov>=4.1.0; extra == "dev"
Requires-Dist: black>=23.0.0; extra == "dev"
Requires-Dist: ruff>=0.1.0; extra == "dev"
Provides-Extra: credibility
Requires-Dist: python-whois>=0.8.0; extra == "credibility"
Provides-Extra: summarizer
Requires-Dist: nltk>=3.8; extra == "summarizer"
Provides-Extra: browser
Requires-Dist: playwright>=1.40.0; extra == "browser"
Dynamic: license-file
